fsner/__init__.py
fsner/model.py
fsner/tokenizer_utils.py
fsner-0.0.3.dist-info/METADATA
fsner-0.0.3.dist-info/WHEEL
fsner-0.0.3.dist-info/top_level.txt
fsner-0.0.3.dist-info/RECORD
