Metadata-Version: 2.1
Name: fsner
Version: 0.0.3
Summary: Few-shot Named Entity Recognition
Home-page: https://github.com/sayef/fsner
Author: msi sayef
Author-email: msi.sayef@gmail.com
License: UNKNOWN
Project-URL: Bug Tracker, https://github.com/sayef/fsner/issues
Platform: UNKNOWN
Classifier: Programming Language :: Python :: 3
Classifier: Operating System :: OS Independent
Requires-Python: >=3.6
Requires-Dist: torch (>=1.9.0)
Requires-Dist: transformers (>=4.9.2)
